lightspider/__init__.py
lightspider/downloader.py
lightspider/scheduler.py
lightspider/spider.py
lightspider/worker.py
lightspider/writer.py
lightspider/baike/__init__.py
lightspider/baike/href.py
lightspider/baike/info.py
lightspider/baike/search.py
lightspider/baike/table.py
lightspider/base/__init__.py
lightspider/utils/__init__.py
lightspider/utils/log.py
lightspider/utils/proxy.py
lightSpider-0.3.0.dist-info/LICENSE
lightSpider-0.3.0.dist-info/METADATA
lightSpider-0.3.0.dist-info/WHEEL
lightSpider-0.3.0.dist-info/top_level.txt
lightSpider-0.3.0.dist-info/RECORD
